README
setup.py
django_utils.egg-info/PKG-INFO
django_utils.egg-info/SOURCES.txt
django_utils.egg-info/dependency_links.txt
django_utils.egg-info/not-zip-safe
django_utils.egg-info/top_level.txt
utils/__init__.py
utils/base.py
utils/fields.py
utils/internal_utils.py
utils/manager.py
utils/models.py
utils/pagination.py
utils/views.py
utils/templatetags/__init__.py
utils/templatetags/smart_humanize.py
utils/templatetags/util_tags.py