Metadata-Version: 1.0
Name: django-utils
Version: 0.0.2
Summary: Utilities for Django
Home-page: http://github.com/ojii/django-utils
Author: Jonas Obrist
Author-email: UNKNOWN
License: UNKNOWN
Platform: OS Independent
Classifier: Environment :: Web Environment
Classifier: Framework :: Django
Classifier: Intended Audience :: Developers
Classifier: License :: OSI Approved :: BSD License
Classifier: Operating System :: OS Independent
Classifier: Programming Language :: Python
Classifier: Topic :: Internet :: WWW/HTTP :: Dynamic Content
Classifier: Topic :: Software Development
Classifier: Topic :: Software Development :: Libraries :: Application Frameworks
Classifier: Development Status :: 4 - Beta
